stonky/__example.cfg
stonky/__init__.py
stonky/__main__.py
stonky/__version__.py
stonky/api.py
stonky/const.py
stonky/enums.py
stonky/exceptions.py
stonky/settings.py
stonky/stock.py
stonky/stock_store.py
stonky/tty.py
stonky-1.4.0.dist-info/METADATA
stonky-1.4.0.dist-info/WHEEL
stonky-1.4.0.dist-info/entry_points.txt
stonky-1.4.0.dist-info/top_level.txt
stonky-1.4.0.dist-info/RECORD
