Metadata-Version: 2.1
Name: stonky
Version: 1.4.0
Summary: A simple command line dashboard for monitoring stocks
Home-page: https://github.com/jkwill87/stonky
Author: Jessy Williams
Author-email: jessy@jessywilliams.com
License: MIT
Platform: UNKNOWN
Requires-Python: ~=3.6
Requires-Dist: aiohttp (==3.*)
Requires-Dist: teletype (>=1.*)
